{
  "project_info": {
    "project_number": "1087009234026",
    "project_id": "project-app1-50732",
    "storage_bucket": "project-app1-50732.appspot.com"
  },
  "client": [
    {
      "client_info": {
        "mobilesdk_app_id": "1:1087009234026:android:83282962461385e6d8fe13",
        "android_client_info": {
          "package_name": "com.example.hotel_app"
        }
      },
      "oauth_client": [
        {
          "client_id": "1087009234026-eso56o46cnoohimnqq68b4qd4uq0kb8i.apps.googleusercontent.com",
          "client_type": 1,
          "android_info": {
            "package_name": "com.example.hotel_app",
            "certificate_hash": "8e56df5ad2fcea638d61d086748d7832c832f568"
          }
        },
        {
          "client_id": "1087009234026-8c726uutfmdkj6s7rarklvm6rjefg7h8.apps.googleusercontent.com",
          "client_type": 3
        }
      ],
      "api_key": [
        {
          "current_key": "AIzaSyAoPyC746_0va3X18RhvtA7l55JG1vpMtY"
        }
      ],
      "services": {
        "appinvite_service": {
          "other_platform_oauth_client": [
            {
              "client_id": "1087009234026-66rh5v38978lm5vfiqnnh7a830upvcem.apps.googleusercontent.com",
              "client_type": 3
            },
            {
              "client_id": "1087009234026-fkrgkut3q9n0cmvnqa9qpesjmqmjinjo.apps.googleusercontent.com",
              "client_type": 2,
              "ios_info": {
                "bundle_id": "com.example.hotelApp"
              }
            }
          ]
        }
      }
    }
  ],
  "configuration_version": "1"
}